{"region_9_partitions_foodgrp_42": {"compotes et fruits cuits": {"compotes": {"coulis de fruits rouges framboises fraises groseilles cassis": 20.0, "compote de fruits divers en conserve": 97.85714285714286, "compote de pomme en conserve": 129.37962962962962, "compote de fruits divers allégée en conserve": 105.0}, "fruits au sirop": {"ananas au sirop en conserve": 143.33333333333334, "poire au sirop en conserve": 100.0, "macédoine de fruits au sirop en conserve": 136.66666666666666, "pêche au sirop en conserve": 130.0, "abricot au sirop en conserve": 60.0}}}}