{"pommes de terre et apparentés": {"sans": {"purée de pomme de terre avec lait et beurre non salée": 145.71428571428572, "pomme de terre rissolée surgelée": 139.93243243243242, "purée de pomme de terre à base de flocons reconstituée au lait demi-écrémé": 190.0, "pomme de terre dauphine cuite": 77.5, "pomme de terre frite surgelée cuite": 80.52631578947368, "pomme de terre cuite à la vapeur": 197.5, "pomme noisette précuite surgelée": 85.0, "pomme de terre cuite au four": 158.88888888888889, "pomme de terre frite non salée": 90.3225806451613, "pomme de terre cuite à l'eau": 173.82291666666666}}}