{"name": "region_21_weekconso_foodgrp_33", "children": [{"name": "1e jour", "children": [{"name": "vin", "children": [{"name": "vin blanc 11°", "size": 98.0}, {"name": "vin rouge 10°", "size": 180.0}, {"name": "vin rouge 11°", "size": 138.0}, {"name": "vin rouge 12°", "size": 207.30769230769232}, {"name": "vin rosé 11°", "size": 166.94117647058823}, {"name": "champagne", "size": 300.0}, {"name": "vin sans précision", "size": 230.0}]}, {"name": "bière", "children": [{"name": "bière brune", "size": 185.0}, {"name": "bière cœur de marché à 4-5° d'alcool type kronenbourg ou 33 export", "size": 270.0}, {"name": "bière de spécialités ou d'abbaye régionales ou de brasserie degré d'alcool varia", "size": 330.0}]}, {"name": "cidre", "children": [{"name": "cidre traditionnel", "size": 250.0}]}, {"name": "spiritueux et vins cuits", "children": [{"name": "liqueurs", "size": 10.5}, {"name": "rhum", "size": 30.0}, {"name": "whisky", "size": 130.0}, {"name": "apéritif à base de vin ou vermouth type martini", "size": 150.0}]}, {"name": "cocktails et mélanges", "children": [{"name": "cocktail alcoolisé", "size": 150.0}, {"name": "pastis prêt à boire (1+5)", "size": 210.0}, {"name": "kir", "size": 100.0}, {"name": "pétillant de fruits", "size": 50.0}]}]}, {"name": "2e jour", "children": [{"name": "vin", "children": [{"name": "vin blanc 11°", "size": 171.42857142857142}, {"name": "vin rouge 10°", "size": 215.0}, {"name": "vin rouge 11°", "size": 186.66666666666666}, {"name": "vin rouge 12°", "size": 226.66666666666666}, {"name": "vin rosé 11°", "size": 201.5}, {"name": "champagne", "size": 100.0}, {"name": "vin rouge 13° et plus", "size": 120.0}, {"name": "vin sans précision", "size": 241.25}]}, {"name": "bière", "children": [{"name": "bière brune", "size": 120.0}, {"name": "bière cœur de marché à 4-5° d'alcool type kronenbourg ou 33 export", "size": 382.14285714285717}, {"name": "bière spéciale à 5-6° d'alcool type 1664 pelforth ambrée ou fischer heineken", "size": 312.5}]}, {"name": "cidre", "children": [{"name": "cidre", "size": 150.0}, {"name": "cidre doux", "size": 300.0}]}, {"name": "spiritueux et vins cuits", "children": [{"name": "eau-de-vie", "size": 40.0}, {"name": "liqueurs", "size": 80.0}, {"name": "whisky", "size": 40.0}, {"name": "apéritif à base de vin ou vermouth type martini", "size": 40.0}, {"name": "apéritif à la gentiane", "size": 15.0}, {"name": "cognac armagnac", "size": 40.0}, {"name": "porto", "size": 75.0}]}, {"name": "cocktails et mélanges", "children": [{"name": "pastis prêt à boire (1+5)", "size": 140.0}, {"name": "sangria", "size": 277.5}, {"name": "kir", "size": 100.0}]}]}, {"name": "3e jour", "children": [{"name": "vin", "children": [{"name": "vin blanc 11°", "size": 228.33333333333334}, {"name": "vin rouge 10°", "size": 207.85714285714286}, {"name": "vin rouge 11°", "size": 230.0}, {"name": "vin rouge 12°", "size": 248.25}, {"name": "vin rosé 11°", "size": 199.2941176470588}, {"name": "champagne", "size": 183.33333333333334}, {"name": "vin sans précision", "size": 194.0}]}, {"name": "bière", "children": [{"name": "bière cœur de marché à 4-5° d'alcool type kronenbourg ou 33 export", "size": 364.0}, {"name": "bière spéciale à 5-6° d'alcool type 1664 pelforth ambrée ou fischer heineken", "size": 300.0}, {"name": "bière de spécialités ou d'abbaye régionales ou de brasserie degré d'alcool varia", "size": 290.0}]}, {"name": "spiritueux et vins cuits", "children": [{"name": "whisky", "size": 53.333333333333336}, {"name": "apéritif à base de vin ou vermouth type martini", "size": 240.0}, {"name": "vodka", "size": 40.0}]}, {"name": "cocktails et mélanges", "children": [{"name": "cocktail alcoolisé", "size": 300.0}, {"name": "pastis prêt à boire (1+5)", "size": 260.0}, {"name": "sangria", "size": 125.0}, {"name": "kir", "size": 300.0}, {"name": "kir royal", "size": 100.0}]}]}, {"name": "4e jour", "children": [{"name": "vin", "children": [{"name": "vin blanc 11°", "size": 314.0}, {"name": "vin blanc mousseux", "size": 100.0}, {"name": "vin rouge 10°", "size": 214.11764705882354}, {"name": "vin rouge 11°", "size": 120.0}, {"name": "vin rouge 12°", "size": 160.0}, {"name": "vin rosé 11°", "size": 197.0}, {"name": "champagne", "size": 200.0}, {"name": "vin sans précision", "size": 206.66666666666666}]}, {"name": "bière", "children": [{"name": "bière cœur de marché à 4-5° d'alcool type kronenbourg ou 33 export", "size": 275.0}, {"name": "bière spéciale à 5-6° d'alcool type 1664 pelforth ambrée ou fischer heineken", "size": 250.0}, {"name": "bière de spécialités ou d'abbaye régionales ou de brasserie degré d'alcool varia", "size": 250.0}]}, {"name": "cidre", "children": [{"name": "cidre doux", "size": 300.0}]}, {"name": "spiritueux et vins cuits", "children": [{"name": "eau-de-vie", "size": 40.0}, {"name": "liqueurs", "size": 50.0}, {"name": "whisky", "size": 120.0}, {"name": "vin doux naturel ou vin muté autre que porto type muscat banyuls ou maury", "size": 100.0}, {"name": "apéritif à base de vin ou vermouth type martini", "size": 45.0}]}, {"name": "cocktails et mélanges", "children": [{"name": "pastis prêt à boire (1+5)", "size": 240.0}, {"name": "kir", "size": 200.0}, {"name": "kir royal", "size": 100.0}]}]}, {"name": "5e jour", "children": [{"name": "vin", "children": [{"name": "vin blanc 11°", "size": 220.25}, {"name": "vin rouge 10°", "size": 186.66666666666666}, {"name": "vin rouge 11°", "size": 180.0}, {"name": "vin rouge 12°", "size": 207.77777777777777}, {"name": "vin rosé 11°", "size": 205.6}, {"name": "champagne", "size": 250.0}, {"name": "vin sans précision", "size": 233.07692307692307}]}, {"name": "bière", "children": [{"name": "bière brune", "size": 125.0}, {"name": "bière cœur de marché à 4-5° d'alcool type kronenbourg ou 33 export", "size": 607.5}, {"name": "bière spéciale à 5-6° d'alcool type 1664 pelforth ambrée ou fischer heineken", "size": 250.0}, {"name": "bière de spécialités ou d'abbaye régionales ou de brasserie degré d'alcool varia", "size": 250.0}]}, {"name": "spiritueux et vins cuits", "children": [{"name": "gin", "size": 40.0}, {"name": "whisky", "size": 50.0}, {"name": "vin doux naturel ou vin muté autre que porto type muscat banyuls ou maury", "size": 50.0}, {"name": "apéritif à base de vin ou vermouth type martini", "size": 50.0}, {"name": "vodka", "size": 40.0}]}, {"name": "cocktails et mélanges", "children": [{"name": "pastis prêt à boire (1+5)", "size": 232.5}, {"name": "kir", "size": 300.0}, {"name": "kir royal", "size": 100.0}, {"name": "panaché", "size": 150.0}]}]}, {"name": "6e jour", "children": [{"name": "vin", "children": [{"name": "vin blanc 11°", "size": 130.66666666666666}, {"name": "vin rouge 10°", "size": 182.0}, {"name": "vin rouge 11°", "size": 293.3333333333333}, {"name": "vin rouge 12°", "size": 152.125}, {"name": "vin rosé 11°", "size": 215.42857142857142}, {"name": "champagne", "size": 100.0}, {"name": "vin sans précision", "size": 227.0}]}, {"name": "bière", "children": [{"name": "bière cœur de marché à 4-5° d'alcool type kronenbourg ou 33 export", "size": 373.3333333333333}, {"name": "bière spéciale à 5-6° d'alcool type 1664 pelforth ambrée ou fischer heineken", "size": 375.0}, {"name": "bière de spécialités ou d'abbaye régionales ou de brasserie degré d'alcool varia", "size": 250.0}]}, {"name": "cidre", "children": [{"name": "cidre", "size": 250.0}]}, {"name": "spiritueux et vins cuits", "children": [{"name": "liqueurs", "size": 50.0}, {"name": "rhum", "size": 40.0}, {"name": "whisky", "size": 60.0}, {"name": "vin doux naturel ou vin muté autre que porto type muscat banyuls ou maury", "size": 250.0}, {"name": "apéritif à base de vin ou vermouth type martini", "size": 50.0}]}, {"name": "cocktails et mélanges", "children": [{"name": "cocktail alcoolisé", "size": 200.0}, {"name": "pastis prêt à boire (1+5)", "size": 200.0}, {"name": "sangria", "size": 330.0}]}]}, {"name": "7e jour", "children": [{"name": "vin", "children": [{"name": "vin blanc 11°", "size": 403.0}, {"name": "vin rouge 10°", "size": 147.36363636363637}, {"name": "vin rouge 11°", "size": 240.0}, {"name": "vin rouge 12°", "size": 234.44444444444446}, {"name": "vin rosé 11°", "size": 247.73333333333332}, {"name": "champagne", "size": 137.5}, {"name": "vin sans précision", "size": 272.14285714285717}]}, {"name": "bière", "children": [{"name": "bière cœur de marché à 4-5° d'alcool type kronenbourg ou 33 export", "size": 386.6666666666667}, {"name": "bière spéciale à 5-6° d'alcool type 1664 pelforth ambrée ou fischer heineken", "size": 475.0}, {"name": "bière de spécialités ou d'abbaye régionales ou de brasserie degré d'alcool varia", "size": 250.0}]}, {"name": "cidre", "children": [{"name": "cidre doux", "size": 240.0}]}, {"name": "spiritueux et vins cuits", "children": [{"name": "pastis", "size": 4.0}, {"name": "eau-de-vie", "size": 50.0}, {"name": "gin", "size": 40.0}, {"name": "whisky", "size": 72.0}, {"name": "vodka", "size": 40.0}, {"name": "cognac armagnac", "size": 40.0}]}, {"name": "cocktails et mélanges", "children": [{"name": "cocktail type punch planteur", "size": 200.0}, {"name": "cocktail alcoolisé", "size": 250.0}, {"name": "pastis prêt à boire (1+5)", "size": 150.0}, {"name": "panaché", "size": 150.0}]}]}]}