{"region_8_partitions_foodgrp_8": {"pâtisseries et gâteaux": {"pâtisseries et tartes": {"tarte ou tartelette aux pommes": 180.6, "pâtisserie sans précision": 112.6923076923077, "millefeuille": 175.0, "chou à la crème chantilly ou pâtissière": 57.916666666666664, "tarte à la crème": 175.0, "tarte ou tartelette aux fruits": 172.27272727272728, "chouquette artisanale": 80.0, "autre pâtisserie": 325.0, "éclair": 113.75}, "gâteaux": {"gâteau moelleux fourré au chocolat ou aux pépites de chocolat noir ou au lait": 42.76923076923077, "pain d'épices": 46.666666666666664, "autre gâteau": 120.0, "gâteau au chocolat": 88.94117647058823, "gâteau moelleux fourré au chocolat multicouches type napolitain lu ou kinder dél": 47.2, "muffin": 95.25, "galette des rois feuilletée fourrée à la frangipane": 160.4516129032258, "gâteau moelleux génoise fourrée à l'orange enrobée de chocolat type pim's": 18.0, "charlotte aux fruits artisanale": 90.0, "gâteau au fromage blanc": 103.5, "gâteau moelleux fourré aux fruits type mini roulé fraise captain choc": 54.0, "baba au rhum": 200.0, "cake aux fruits": 67.85714285714286, "madeleine": 69.6875, "gâteau à la crème": 116.5625, "gâteau sans précision": 103.79166666666667, "gâteau mousse aux fruits sur génoise type miroir aux fruits rouges de picard": 146.36363636363637, "brownie au chocolat": 43.75, "quatre-quarts fabrication industrielle": 55.0}, "beignets, crêpes et gaufres": {"crêpe au froment fourrée au chocolat ou ou à la pâte à tartiner chocolat et nois": 57.0, "crêpe ou galette bretonne au blé noir ou sarrasin": 52.583333333333336, "crêpe au froment sucrée non fourrée": 168.33333333333334, "beignet fourré aux fruits": 53.2, "crêpe au froment nature": 167.30434782608697, "beignet fourré à la confiture": 35.0, "pain perdu": 85.0, "beignet sucré nature": 55.0, "gaufre bruxelloise ou liégeoise avec ou sans chocolat préemballée": 56.98837209302326, "crêpe au froment fourrée à la confiture": 86.0}}}}