{"glaces et desserts glacés": {"desserts glacés": {"barre chocolatée glacée type mars twix snickers": 55.333333333333336, "pêche melba": 175.0, "profiteroles glace vanille et sauce chocolat": 250.0}, "glaces": {"crème glacée à la vanille type carte d'or vanille": 110.425, "glace en cornet": 115.45454545454545, "crème glacée au chocolat type carte d'or chocolat": 70.0, "glace crème glacée sorbet ou glace à l'eau parfums divers": 84.44444444444444, "glace enrobée de chocolat type esquimau": 85.45}, "sorbets": {"sorbet tout type": 104.0}}}