{"name": "region_3_weekconso_foodgrp_3", "children": [{"name": "1e jour enregistrement", "children": [{"name": "pâtes alimentaires", "children": [{"name": "pâtes alimentaires cuites", "size": 151.48936170212767}]}]}, {"name": "2e jour enregistrement", "children": [{"name": "pâtes alimentaires", "children": [{"name": "pâtes alimentaires cuites", "size": 177.8125}, {"name": "pâtes alimentaires aux oeufs cuites", "size": 200.0}]}]}, {"name": "3e jour enregistrement", "children": [{"name": "pâtes alimentaires", "children": [{"name": "pâtes alimentaires cuites", "size": 134.45652173913044}, {"name": "pâtes alimentaires aux oeufs cuites", "size": 200.0}]}]}, {"name": "4e jour enregistrement", "children": [{"name": "pâtes alimentaires", "children": [{"name": "pâtes alimentaires cuites", "size": 183.125}, {"name": "pâtes alimentaires aux oeufs cuites", "size": 350.0}, {"name": "pâtes alimentaires au blé complet cuites", "size": 150.0}]}]}, {"name": "5e jour enregistrement", "children": [{"name": "pâtes alimentaires", "children": [{"name": "pâtes alimentaires cuites", "size": 164.0909090909091}, {"name": "pâtes alimentaires au blé complet cuites", "size": 150.0}]}]}, {"name": "6e jour enregistrement", "children": [{"name": "pâtes alimentaires", "children": [{"name": "pâtes alimentaires cuites", "size": 152.28571428571428}]}]}, {"name": "7e jour enregistrement", "children": [{"name": "pâtes alimentaires", "children": [{"name": "pâtes alimentaires cuites", "size": 145.71428571428572}, {"name": "pâtes alimentaires aux oeufs cuites", "size": 100.0}, {"name": "pâtes alimentaires au blé complet cuites", "size": 150.0}]}]}]}