{"region_12_partitions_foodgrp_8": {"pâtisseries et gâteaux": {"pâtisseries et tartes": {"tarte ou tartelette aux pommes": 176.85185185185185, "pâtisserie orientale aux amandes et au sirop": 140.0, "pâtisserie sans précision": 80.625, "crumble aux pommes": 172.0, "millefeuille": 43.0, "tarte à la crème": 180.0, "tarte ou tartelette aux fruits": 156.3709677419355, "chouquette artisanale": 76.0, "macaron moelleux fourré à la confiture ou à la crème artisanal": 68.25, "autre pâtisserie": 180.0, "éclair": 87.66666666666667}, "gâteaux": {"gâteau moelleux fourré au chocolat ou aux pépites de chocolat noir ou au lait": 48.55, "pain d'épices": 76.66666666666667, "autre gâteau": 88.08333333333333, "gâteau au chocolat": 93.09375, "gâteau moelleux fourré au chocolat multicouches type napolitain lu ou kinder dél": 42.0, "muffin": 75.0, "galette des rois feuilletée fourrée à la frangipane": 152.1951219512195, "gâteau moelleux génoise fourrée à l'orange enrobée de chocolat type pim's": 45.0, "cake aux fruits": 68.92307692307692, "gâteau au fromage blanc": 128.92857142857142, "quatre-quarts fabrication industrielle": 91.92307692307692, "gâteau breton ou far aux pruneau": 55.0, "gâteau de savoie": 105.0, "madeleine": 67.40298507462687, "gâteau à la crème": 130.27272727272728, "gâteau sans précision": 86.05263157894737, "gâteau mousse aux fruits sur génoise type miroir aux fruits rouges de picard": 105.9090909090909, "brownie au chocolat": 79.58333333333333, "gâteau moelleux fourré aux fruits type mini roulé fraise captain choc": 33.4}, "beignets, crêpes et gaufres": {"crêpe au froment fourrée au chocolat ou ou à la pâte à tartiner chocolat et nois": 93.55555555555556, "gaufre bruxelloise ou liégeoise avec ou sans chocolat préemballée": 74.5, "blinis": 140.0, "crêpe au froment sucrée non fourrée": 176.0, "beignet fourré aux fruits": 50.0, "crêpe au froment nature": 117.6953125, "beignet fourré à la confiture": 35.0, "pain perdu": 100.0, "beignet sucré nature": 49.166666666666664, "crêpe ou galette bretonne au blé noir ou sarrasin": 103.97058823529412, "crêpe au froment fourrée à la confiture": 160.0}}}}