{"region_4_partitions_foodgrp_30": {"sucres et dérivés": {"confiserie": {"bonbons gélifiés": 13.0, "confiserie dragéifiée au chocolat type smarties": 14.6, "pâte d'amande fabrication industrielle": 25.0, "meringue": 14.0, "chewing-gum sucré": 6.285714285714286, "confiserie à base de cacahuètes dragéifiées enrobées de chocolat type m&ms cacah": 39.0, "bonbons tout type sauf gélifiés": 17.738095238095237, "chewing-gum sans sucre": 4.75}, "confiture et miel": {"miel": 10.268292682926829, "confiture ajoutée au service": 9.418604651162791, "confiture d'orange": 20.625, "confiture de fraise": 27.692307692307693, "confiture d'abricot": 29.0, "confiture ou marmelade tout type": 24.065420560747665, "confiture allégée": 18.928571428571427}, "sucre et assimilés": {"sucre roux": 7.858974358974359, "sucre blanc": 8.154462242562929, "sucre blanc ajouté au service": 6.3175675675675675}}}}