{"name": "region_2_weekconso_foodgrp_11", "children": [{"name": "1e jour", "children": [{"name": "fromages affin\u00e9s", "children": [{"name": "camembert fromage \u00e0 p\u00e2te molle \u00e0 cro\u00fbte fleurie 45% m.g.", "size": 53.5}, {"name": "fromage \u00e0 p\u00e2te molle \u00e0 cro\u00fbte fleurie genre camembert all\u00e9g\u00e9 20-30% m.g.", "size": 50.0}, {"name": "coulommiers fromage \u00e0 p\u00e2te molle \u00e0 cro\u00fbte fleurie 40-45% m.g.", "size": 30.0}, {"name": "brie fromage \u00e0 p\u00e2te molle \u00e0 cro\u00fbte fleurie 45% m.g.", "size": 48.75}, {"name": "chaource fromage \u00e0 p\u00e2te molle \u00e0 cro\u00fbte fleurie 50% m.g.", "size": 80.0}, {"name": "munster fromage \u00e0 p\u00e2te molle \u00e0 cro\u00fbte lav\u00e9e 45-50% m.g.", "size": 30.0}, {"name": "reblochon fromage \u00e0 p\u00e2te press\u00e9e non cuite 45% m.g.", "size": 30.0}, {"name": "rouy fromage \u00e0 p\u00e2te molle \u00e0 cro\u00fbte lav\u00e9e 40% m.g.", "size": 30.0}, {"name": "comt\u00e9 fromage \u00e0 p\u00e2te press\u00e9e cuite 45% m.g.", "size": 80.0}, {"name": "gruy\u00e8re fromage \u00e0 p\u00e2te press\u00e9e cuite 45% m.g.", "size": 27.2}, {"name": "emmental fromage \u00e0 p\u00e2te press\u00e9e cuite 45% m.g.", "size": 37.333333333333336}, {"name": "emmental all\u00e9g\u00e9", "size": 33.0}, {"name": "roquefort fromage de brebis \u00e0 p\u00e2te persill\u00e9e 52% m.g.", "size": 30.0}, {"name": "bleu et mini bleu de bresse fromage \u00e0 p\u00e2te persill\u00e9e 45% m.g.", "size": 20.0}, {"name": "fromage et mini fromage type bonbel-babybel", "size": 30.0}, {"name": "\u00e9dam fromage \u00e0 p\u00e2te press\u00e9e non cuite 40-45% m.g.", "size": 30.0}, {"name": "mimolette fromage \u00e0 p\u00e2te press\u00e9e non cuite 45% m.g.", "size": 20.0}, {"name": "fromage des pyr\u00e9n\u00e9es au lait de brebis", "size": 10.0}, {"name": "saint-nectaire fromage \u00e0 p\u00e2te press\u00e9e non cuite 45% m.g.", "size": 15.0}, {"name": "tomme de montagne ou tomme de savoie", "size": 30.0}, {"name": "fromage sans pr\u00e9cision", "size": 37.142857142857146}, {"name": "camembert sans pr\u00e9cision", "size": 39.411764705882355}, {"name": "caprice des dieux fromage \u00e0 p\u00e2te molle 60% m.g.", "size": 40.0}, {"name": "chamois d'or fromage \u00e0 p\u00e2te molle 60% m.g.", "size": 30.0}, {"name": "saint albray fromage \u00e0 p\u00e2te molle 50% m.g.", "size": 60.0}, {"name": "selles-sur-cher fromage de ch\u00e8vre", "size": 80.0}, {"name": "fromage de ch\u00e8vre mi-sec", "size": 25.0}, {"name": "crottin fromage de ch\u00e8vre", "size": 15.0}, {"name": "sainte-maure fromage de ch\u00e8vre", "size": 40.0}]}, {"name": "fromages fondus", "children": [{"name": "fromage fondu 25% m.g. type sylphide ou vache qui rit \u00e9quilibre et ligne", "size": 20.0}, {"name": "fromage de ch\u00e8vre fondu \u00e0 tartiner nature type cabrette ou chavroux", "size": 30.0}, {"name": "ap\u00e9ricube fromage fondu 50% m.g.", "size": 40.0}, {"name": "kiri cr\u00e8me fromage fondu double cr\u00e8me 70% m.g.", "size": 20.0}, {"name": "vache qui rit fromage fondu 50% m.g.", "size": 21.5}]}, {"name": "fromages frais non affin\u00e9s", "children": [{"name": "f\u00e9ta de brebis", "size": 40.0}, {"name": "fromage frais \u00e0 tartiner 40-60% m.g", "size": 20.0}, {"name": "boursin fromage frais sal\u00e9 aromatis\u00e9 70% m.g.", "size": 25.0}]}]}, {"name": "2e jour", "children": [{"name": "fromages affin\u00e9s", "children": [{"name": "camembert fromage \u00e0 p\u00e2te molle \u00e0 cro\u00fbte fleurie 45% m.g.", "size": 51.5}, {"name": "fromage \u00e0 p\u00e2te molle \u00e0 cro\u00fbte fleurie genre camembert all\u00e9g\u00e9 20-30% m.g.", "size": 60.0}, {"name": "coulommiers fromage \u00e0 p\u00e2te molle \u00e0 cro\u00fbte fleurie 40-45% m.g.", "size": 41.666666666666664}, {"name": "brie fromage \u00e0 p\u00e2te molle \u00e0 cro\u00fbte fleurie 45% m.g.", "size": 30.0}, {"name": "chaource fromage \u00e0 p\u00e2te molle \u00e0 cro\u00fbte fleurie 50% m.g.", "size": 20.0}, {"name": "reblochon fromage \u00e0 p\u00e2te press\u00e9e non cuite 45% m.g.", "size": 15.0}, {"name": "gruy\u00e8re fromage \u00e0 p\u00e2te press\u00e9e cuite 45% m.g.", "size": 23.5}, {"name": "emmental fromage \u00e0 p\u00e2te press\u00e9e cuite 45% m.g.", "size": 37.5}, {"name": "emmental all\u00e9g\u00e9", "size": 40.0}, {"name": "roquefort fromage de brebis \u00e0 p\u00e2te persill\u00e9e 52% m.g.", "size": 27.857142857142858}, {"name": "bleu d'auvergne fromage \u00e0 p\u00e2te persill\u00e9e 50% m.g.", "size": 40.0}, {"name": "fromage \u00e0 p\u00e2te press\u00e9e non cuite 40-50% m.g.", "size": 20.0}, {"name": "fromage et mini fromage type bonbel-babybel", "size": 30.0}, {"name": "mimolette fromage \u00e0 p\u00e2te press\u00e9e non cuite 45% m.g.", "size": 30.0}, {"name": "raclette fromage \u00e0 p\u00e2te press\u00e9e non cuite 45% m.g.", "size": 340.0}, {"name": "tomme de montagne ou tomme de savoie", "size": 20.0}, {"name": "fromage de ch\u00e8vre affin\u00e9 au lait pasteuris\u00e9 ou cru", "size": 33.333333333333336}, {"name": "fromage sans pr\u00e9cision", "size": 41.25}, {"name": "camembert sans pr\u00e9cision", "size": 38.75}, {"name": "caprice des dieux fromage \u00e0 p\u00e2te molle 60% m.g.", "size": 15.0}, {"name": "fromage de ch\u00e8vre mi-sec", "size": 26.666666666666668}, {"name": "crottin fromage de ch\u00e8vre", "size": 20.0}, {"name": "sainte-maure fromage de ch\u00e8vre", "size": 40.0}]}, {"name": "fromages fondus", "children": [{"name": "fromage fondu 25% m.g. type sylphide ou vache qui rit \u00e9quilibre et ligne", "size": 48.0}, {"name": "fromage de ch\u00e8vre fondu \u00e0 tartiner nature type cabrette ou chavroux", "size": 10.0}, {"name": "saint-moret all\u00e9g\u00e9 fromage fondu demi-sel 20% m.g.", "size": 16.0}, {"name": "samos 99 fromage fondu double cr\u00e8me 70% m.g.", "size": 25.0}, {"name": "vache qui rit fromage fondu 50% m.g.", "size": 21.6}]}, {"name": "fromages frais non affin\u00e9s", "children": [{"name": "f\u00e9ta de brebis", "size": 40.0}, {"name": "ricotta", "size": 30.0}, {"name": "mozzarella", "size": 30.0}, {"name": "boursin fromage frais sal\u00e9 aromatis\u00e9 70% m.g.", "size": 33.75}, {"name": "carr\u00e9 frais fromage \u00e0 tartiner 40% m.g.", "size": 25.0}, {"name": "tartare fromage frais aromatis\u00e9 sal\u00e9 70% m.g.", "size": 20.0}]}]}, {"name": "3e jour", "children": [{"name": "fromages affin\u00e9s", "children": [{"name": "camembert fromage \u00e0 p\u00e2te molle \u00e0 cro\u00fbte fleurie 45% m.g.", "size": 58.333333333333336}, {"name": "camembert et apparent\u00e9s 50% m.g.", "size": 30.0}, {"name": "fromage \u00e0 p\u00e2te molle \u00e0 cro\u00fbte fleurie genre camembert all\u00e9g\u00e9 20-30% m.g.", "size": 60.0}, {"name": "coulommiers fromage \u00e0 p\u00e2te molle \u00e0 cro\u00fbte fleurie 40-45% m.g.", "size": 30.0}, {"name": "brie fromage \u00e0 p\u00e2te molle \u00e0 cro\u00fbte fleurie 45% m.g.", "size": 30.0}, {"name": "munster fromage \u00e0 p\u00e2te molle \u00e0 cro\u00fbte lav\u00e9e 45-50% m.g.", "size": 30.0}, {"name": "rouy fromage \u00e0 p\u00e2te molle \u00e0 cro\u00fbte lav\u00e9e 40% m.g.", "size": 37.5}, {"name": "comt\u00e9 fromage \u00e0 p\u00e2te press\u00e9e cuite 45% m.g.", "size": 50.0}, {"name": "gruy\u00e8re fromage \u00e0 p\u00e2te press\u00e9e cuite 45% m.g.", "size": 32.4}, {"name": "emmental fromage \u00e0 p\u00e2te press\u00e9e cuite 45% m.g.", "size": 46.0}, {"name": "emmental all\u00e9g\u00e9", "size": 40.0}, {"name": "roquefort fromage de brebis \u00e0 p\u00e2te persill\u00e9e 52% m.g.", "size": 17.5}, {"name": "fromage \u00e0 p\u00e2te press\u00e9e non cuite 40-50% m.g.", "size": 20.0}, {"name": "fromage et mini fromage type bonbel-babybel", "size": 30.0}, {"name": "gouda fromage \u00e0 p\u00e2te press\u00e9e non cuite 30-40% m.g.", "size": 20.0}, {"name": "mimolette fromage \u00e0 p\u00e2te press\u00e9e non cuite 45% m.g.", "size": 35.0}, {"name": "raclette fromage \u00e0 p\u00e2te press\u00e9e non cuite 45% m.g.", "size": 100.0}, {"name": "saint-nectaire fromage \u00e0 p\u00e2te press\u00e9e non cuite 45% m.g.", "size": 20.0}, {"name": "fromage de ch\u00e8vre affin\u00e9 au lait pasteuris\u00e9 ou cru", "size": 30.0}, {"name": "fromage sans pr\u00e9cision", "size": 37.72727272727273}, {"name": "fromage \u00e0 cuire pan\u00e9 au jambon type menu fromage", "size": 75.0}, {"name": "camembert sans pr\u00e9cision", "size": 41.875}, {"name": "caprice des dieux fromage \u00e0 p\u00e2te molle 60% m.g.", "size": 60.0}, {"name": "leerdammer fromage \u00e0 p\u00e2te press\u00e9e demi-cuite \u00e0 trous 45% m.g.", "size": 40.0}, {"name": "vieux pan\u00e9 fromage \u00e0 p\u00e2te molle 50% m.g.", "size": 45.0}, {"name": "selles-sur-cher fromage de ch\u00e8vre", "size": 40.0}, {"name": "fromage de ch\u00e8vre mi-sec", "size": 16.666666666666668}]}, {"name": "fromages fondus", "children": [{"name": "fromage fondu 25% m.g. type sylphide ou vache qui rit \u00e9quilibre et ligne", "size": 36.5}, {"name": "fromage de ch\u00e8vre fondu \u00e0 tartiner nature type cabrette ou chavroux", "size": 5.0}, {"name": "kiri cr\u00e8me fromage fondu double cr\u00e8me 70% m.g.", "size": 22.5}, {"name": "saint-moret fromage fondu demi-sel 30% m.g.", "size": 20.0}, {"name": "samos 99 fromage fondu double cr\u00e8me 70% m.g.", "size": 25.0}, {"name": "vache qui rit fromage fondu 50% m.g.", "size": 16.0}]}, {"name": "fromages frais non affin\u00e9s", "children": [{"name": "boursin fromage frais sal\u00e9 aromatis\u00e9 70% m.g.", "size": 22.0}, {"name": "carr\u00e9 frais fromage \u00e0 tartiner 40% m.g.", "size": 50.0}]}]}, {"name": "4e jour", "children": [{"name": "fromages affin\u00e9s", "children": [{"name": "camembert fromage \u00e0 p\u00e2te molle \u00e0 cro\u00fbte fleurie 45% m.g.", "size": 80.0}, {"name": "fromage \u00e0 p\u00e2te molle \u00e0 cro\u00fbte fleurie genre camembert all\u00e9g\u00e9 20-30% m.g.", "size": 60.0}, {"name": "coulommiers fromage \u00e0 p\u00e2te molle \u00e0 cro\u00fbte fleurie 40-45% m.g.", "size": 50.0}, {"name": "brie fromage \u00e0 p\u00e2te molle \u00e0 cro\u00fbte fleurie 45% m.g.", "size": 30.0}, {"name": "chaource fromage \u00e0 p\u00e2te molle \u00e0 cro\u00fbte fleurie 50% m.g.", "size": 20.0}, {"name": "munster fromage \u00e0 p\u00e2te molle \u00e0 cro\u00fbte lav\u00e9e 45-50% m.g.", "size": 15.0}, {"name": "reblochon fromage \u00e0 p\u00e2te press\u00e9e non cuite 45% m.g.", "size": 25.0}, {"name": "autre fromage \u00e0 p\u00e2te press\u00e9e cuite", "size": 24.0}, {"name": "comt\u00e9 fromage \u00e0 p\u00e2te press\u00e9e cuite 45% m.g.", "size": 40.0}, {"name": "gruy\u00e8re fromage \u00e0 p\u00e2te press\u00e9e cuite 45% m.g.", "size": 48.44444444444444}, {"name": "emmental fromage \u00e0 p\u00e2te press\u00e9e cuite 45% m.g.", "size": 140.0}, {"name": "roquefort fromage de brebis \u00e0 p\u00e2te persill\u00e9e 52% m.g.", "size": 45.714285714285715}, {"name": "bleu au lait de vache fromage \u00e0 p\u00e2te persill\u00e9e sans pr\u00e9cision", "size": 40.0}, {"name": "bleu d'auvergne fromage \u00e0 p\u00e2te persill\u00e9e 50% m.g.", "size": 40.0}, {"name": "bleu et mini bleu de bresse fromage \u00e0 p\u00e2te persill\u00e9e 45% m.g.", "size": 30.0}, {"name": "fromage \u00e0 p\u00e2te press\u00e9e non cuite 40-50% m.g.", "size": 45.0}, {"name": "gouda fromage \u00e0 p\u00e2te press\u00e9e non cuite 30-40% m.g.", "size": 20.0}, {"name": "mimolette fromage \u00e0 p\u00e2te press\u00e9e non cuite 45% m.g.", "size": 30.0}, {"name": "morbier fromage \u00e0 p\u00e2te press\u00e9e non cuite 45% m.g.", "size": 15.0}, {"name": "fromage des pyr\u00e9n\u00e9es au lait de brebis", "size": 10.0}, {"name": "raclette fromage \u00e0 p\u00e2te press\u00e9e non cuite 45% m.g.", "size": 110.0}, {"name": "saint-nectaire fromage \u00e0 p\u00e2te press\u00e9e non cuite 45% m.g.", "size": 15.0}, {"name": "saint-paulin fromage \u00e0 p\u00e2te press\u00e9e non cuite 45-50% m.g.", "size": 30.0}, {"name": "tome ou tomme fromage \u00e0 p\u00e2te press\u00e9e non cuite 45% m.g.", "size": 20.0}, {"name": "fromage de ch\u00e8vre affin\u00e9 au lait pasteuris\u00e9 ou cru", "size": 36.666666666666664}, {"name": "fromage sans pr\u00e9cision", "size": 58.75}, {"name": "camembert sans pr\u00e9cision", "size": 39.25}, {"name": "caprice des dieux fromage \u00e0 p\u00e2te molle 60% m.g.", "size": 75.0}, {"name": "vieux pan\u00e9 fromage \u00e0 p\u00e2te molle 50% m.g.", "size": 60.0}, {"name": "maasdam fromage \u00e0 p\u00e2te press\u00e9e non cuite \u00e0 trous 45% m.g.", "size": 40.0}, {"name": "fromage de ch\u00e8vre mi-sec", "size": 33.333333333333336}]}, {"name": "fromages fondus", "children": [{"name": "fromage fondu 25% m.g. type sylphide ou vache qui rit \u00e9quilibre et ligne", "size": 48.0}, {"name": "cancoillotte sp\u00e9cialit\u00e9 fromag\u00e8re fondue 40% m.g.", "size": 15.0}, {"name": "ap\u00e9ricube fromage fondu 50% m.g.", "size": 17.5}, {"name": "p'tit louis fromage fondu 65% m.g.", "size": 20.0}, {"name": "saint-moret fromage fondu demi-sel 30% m.g.", "size": 20.0}, {"name": "vache qui rit fromage fondu 50% m.g.", "size": 27.6}]}, {"name": "fromages frais non affin\u00e9s", "children": [{"name": "boursin fromage frais sal\u00e9 aromatis\u00e9 70% m.g.", "size": 34.5}, {"name": "carr\u00e9 frais fromage \u00e0 tartiner 40% m.g.", "size": 50.0}]}, {"name": "autres fromages ou fromage sans pr\u00e9cision", "children": [{"name": "autre fromage", "size": 40.0}]}]}, {"name": "5e jour", "children": [{"name": "fromages affin\u00e9s", "children": [{"name": "camembert fromage \u00e0 p\u00e2te molle \u00e0 cro\u00fbte fleurie 45% m.g.", "size": 67.0}, {"name": "camembert et apparent\u00e9s 50% m.g.", "size": 60.0}, {"name": "coulommiers fromage \u00e0 p\u00e2te molle \u00e0 cro\u00fbte fleurie 40-45% m.g.", "size": 45.0}, {"name": "brie fromage \u00e0 p\u00e2te molle \u00e0 cro\u00fbte fleurie 45% m.g.", "size": 15.0}, {"name": "chaource fromage \u00e0 p\u00e2te molle \u00e0 cro\u00fbte fleurie 50% m.g.", "size": 30.0}, {"name": "reblochon fromage \u00e0 p\u00e2te press\u00e9e non cuite 45% m.g.", "size": 23.333333333333332}, {"name": "comt\u00e9 fromage \u00e0 p\u00e2te press\u00e9e cuite 45% m.g.", "size": 46.666666666666664}, {"name": "gruy\u00e8re fromage \u00e0 p\u00e2te press\u00e9e cuite 45% m.g.", "size": 35.857142857142854}, {"name": "emmental fromage \u00e0 p\u00e2te press\u00e9e cuite 45% m.g.", "size": 60.0}, {"name": "emmental all\u00e9g\u00e9", "size": 41.333333333333336}, {"name": "roquefort fromage de brebis \u00e0 p\u00e2te persill\u00e9e 52% m.g.", "size": 20.0}, {"name": "fromage et mini fromage type bonbel-babybel", "size": 20.0}, {"name": "gouda fromage \u00e0 p\u00e2te press\u00e9e non cuite 30-40% m.g.", "size": 32.5}, {"name": "mimolette fromage \u00e0 p\u00e2te press\u00e9e non cuite 45% m.g.", "size": 30.0}, {"name": "morbier fromage \u00e0 p\u00e2te press\u00e9e non cuite 45% m.g.", "size": 20.0}, {"name": "fromage des pyr\u00e9n\u00e9es au lait de brebis", "size": 10.0}, {"name": "tome ou tomme fromage \u00e0 p\u00e2te press\u00e9e non cuite 45% m.g.", "size": 30.0}, {"name": "fromage de ch\u00e8vre affin\u00e9 au lait pasteuris\u00e9 ou cru", "size": 40.0}, {"name": "fromage sans pr\u00e9cision", "size": 35.0}, {"name": "camembert sans pr\u00e9cision", "size": 36.76470588235294}, {"name": "caprice des dieux fromage \u00e0 p\u00e2te molle 60% m.g.", "size": 67.5}, {"name": "leerdammer fromage \u00e0 p\u00e2te press\u00e9e demi-cuite \u00e0 trous 45% m.g.", "size": 30.0}, {"name": "fromage de ch\u00e8vre mi-sec", "size": 20.0}]}, {"name": "fromages fondus", "children": [{"name": "fromage fondu 25% m.g. type sylphide ou vache qui rit \u00e9quilibre et ligne", "size": 48.0}, {"name": "p'tit louis fromage fondu 65% m.g.", "size": 20.0}, {"name": "saint-moret fromage fondu demi-sel 30% m.g.", "size": 25.0}, {"name": "samos 99 fromage fondu double cr\u00e8me 70% m.g.", "size": 25.0}, {"name": "vache qui rit fromage fondu 50% m.g.", "size": 28.666666666666668}]}, {"name": "fromages frais non affin\u00e9s", "children": [{"name": "fromage frais \u00e0 tartiner 40-60% m.g", "size": 100.0}, {"name": "mozzarella", "size": 40.0}, {"name": "boursin fromage frais sal\u00e9 aromatis\u00e9 70% m.g.", "size": 41.666666666666664}, {"name": "tartare fromage frais aromatis\u00e9 sal\u00e9 70% m.g.", "size": 25.0}]}, {"name": "autres fromages ou fromage sans pr\u00e9cision", "children": [{"name": "autre fromage", "size": 40.0}]}]}, {"name": "6e jour", "children": [{"name": "fromages affin\u00e9s", "children": [{"name": "camembert fromage \u00e0 p\u00e2te molle \u00e0 cro\u00fbte fleurie 45% m.g.", "size": 60.714285714285715}, {"name": "camembert et apparent\u00e9s 50% m.g.", "size": 30.0}, {"name": "fromage \u00e0 p\u00e2te molle \u00e0 cro\u00fbte fleurie genre camembert all\u00e9g\u00e9 20-30% m.g.", "size": 60.0}, {"name": "coulommiers fromage \u00e0 p\u00e2te molle \u00e0 cro\u00fbte fleurie 40-45% m.g.", "size": 46.666666666666664}, {"name": "brie fromage \u00e0 p\u00e2te molle \u00e0 cro\u00fbte fleurie 45% m.g.", "size": 30.0}, {"name": "chaource fromage \u00e0 p\u00e2te molle \u00e0 cro\u00fbte fleurie 50% m.g.", "size": 45.0}, {"name": "reblochon fromage \u00e0 p\u00e2te press\u00e9e non cuite 45% m.g.", "size": 75.0}, {"name": "rouy fromage \u00e0 p\u00e2te molle \u00e0 cro\u00fbte lav\u00e9e 40% m.g.", "size": 30.0}, {"name": "comt\u00e9 fromage \u00e0 p\u00e2te press\u00e9e cuite 45% m.g.", "size": 20.0}, {"name": "gruy\u00e8re fromage \u00e0 p\u00e2te press\u00e9e cuite 45% m.g.", "size": 29.11111111111111}, {"name": "emmental fromage \u00e0 p\u00e2te press\u00e9e cuite 45% m.g.", "size": 45.0}, {"name": "emmental all\u00e9g\u00e9", "size": 60.0}, {"name": "roquefort fromage de brebis \u00e0 p\u00e2te persill\u00e9e 52% m.g.", "size": 53.333333333333336}, {"name": "fromage \u00e0 p\u00e2te press\u00e9e non cuite 40-50% m.g.", "size": 40.0}, {"name": "fromage et mini fromage type bonbel-babybel", "size": 30.0}, {"name": "\u00e9dam fromage \u00e0 p\u00e2te press\u00e9e non cuite 40-45% m.g.", "size": 30.0}, {"name": "gouda fromage \u00e0 p\u00e2te press\u00e9e non cuite 30-40% m.g.", "size": 25.0}, {"name": "morbier fromage \u00e0 p\u00e2te press\u00e9e non cuite 45% m.g.", "size": 10.0}, {"name": "fromage des pyr\u00e9n\u00e9es au lait de brebis", "size": 10.0}, {"name": "saint-nectaire fromage \u00e0 p\u00e2te press\u00e9e non cuite 45% m.g.", "size": 30.0}, {"name": "tome ou tomme fromage \u00e0 p\u00e2te press\u00e9e non cuite 45% m.g.", "size": 60.0}, {"name": "fromage sans pr\u00e9cision", "size": 45.55555555555556}, {"name": "camembert sans pr\u00e9cision", "size": 41.666666666666664}, {"name": "caprice des dieux fromage \u00e0 p\u00e2te molle 60% m.g.", "size": 67.5}, {"name": "fromage de ch\u00e8vre mi-sec", "size": 16.666666666666668}, {"name": "crottin fromage de ch\u00e8vre", "size": 40.0}]}, {"name": "fromages fondus", "children": [{"name": "fromage fondu 25% m.g. type sylphide ou vache qui rit \u00e9quilibre et ligne", "size": 48.0}, {"name": "kiri cr\u00e8me fromage fondu double cr\u00e8me 70% m.g.", "size": 20.0}, {"name": "saint-moret fromage fondu demi-sel 30% m.g.", "size": 43.333333333333336}, {"name": "saint-moret all\u00e9g\u00e9 fromage fondu demi-sel 20% m.g.", "size": 16.0}, {"name": "vache qui rit fromage fondu 50% m.g.", "size": 50.0}]}, {"name": "fromages frais non affin\u00e9s", "children": [{"name": "fromage frais \u00e0 tartiner nature \u00e0 plus de 60% m.g.", "size": 20.0}, {"name": "boursin fromage frais sal\u00e9 aromatis\u00e9 70% m.g.", "size": 32.0}]}]}, {"name": "7e jour", "children": [{"name": "fromages affin\u00e9s", "children": [{"name": "camembert fromage \u00e0 p\u00e2te molle \u00e0 cro\u00fbte fleurie 45% m.g.", "size": 65.0}, {"name": "coulommiers fromage \u00e0 p\u00e2te molle \u00e0 cro\u00fbte fleurie 40-45% m.g.", "size": 30.0}, {"name": "brie fromage \u00e0 p\u00e2te molle \u00e0 cro\u00fbte fleurie 45% m.g.", "size": 60.0}, {"name": "reblochon fromage \u00e0 p\u00e2te press\u00e9e non cuite 45% m.g.", "size": 67.5}, {"name": "rouy fromage \u00e0 p\u00e2te molle \u00e0 cro\u00fbte lav\u00e9e 40% m.g.", "size": 45.0}, {"name": "gruy\u00e8re fromage \u00e0 p\u00e2te press\u00e9e cuite 45% m.g.", "size": 22.5}, {"name": "emmental fromage \u00e0 p\u00e2te press\u00e9e cuite 45% m.g.", "size": 64.0}, {"name": "emmental all\u00e9g\u00e9", "size": 40.0}, {"name": "\u00e9dam fromage \u00e0 p\u00e2te press\u00e9e non cuite 40-45% m.g.", "size": 30.0}, {"name": "gouda fromage \u00e0 p\u00e2te press\u00e9e non cuite 30-40% m.g.", "size": 10.0}, {"name": "morbier fromage \u00e0 p\u00e2te press\u00e9e non cuite 45% m.g.", "size": 10.0}, {"name": "saint-nectaire fromage \u00e0 p\u00e2te press\u00e9e non cuite 45% m.g.", "size": 35.0}, {"name": "saint-paulin fromage \u00e0 p\u00e2te press\u00e9e non cuite 45-50% m.g.", "size": 40.0}, {"name": "fromage de ch\u00e8vre p\u00e2te molle", "size": 40.0}, {"name": "fromage sans pr\u00e9cision", "size": 39.23076923076923}, {"name": "camembert sans pr\u00e9cision", "size": 38.57142857142857}, {"name": "caprice des dieux fromage \u00e0 p\u00e2te molle 60% m.g.", "size": 67.5}, {"name": "chaumes fromage \u00e0 p\u00e2te molle \u00e0 cro\u00fbte lav\u00e9e 50% m.g.", "size": 60.0}, {"name": "maasdam fromage \u00e0 p\u00e2te press\u00e9e non cuite \u00e0 trous 45% m.g.", "size": 80.0}, {"name": "fromage de ch\u00e8vre mi-sec", "size": 20.0}]}, {"name": "fromages fondus", "children": [{"name": "fromage fondu 25% m.g. type sylphide ou vache qui rit \u00e9quilibre et ligne", "size": 48.0}, {"name": "p'tit louis fromage fondu 65% m.g.", "size": 20.0}, {"name": "saint-moret fromage fondu demi-sel 30% m.g.", "size": 32.5}, {"name": "saint-moret all\u00e9g\u00e9 fromage fondu demi-sel 20% m.g.", "size": 20.0}, {"name": "samos 99 fromage fondu double cr\u00e8me 70% m.g.", "size": 25.0}, {"name": "vache qui rit fromage fondu 50% m.g.", "size": 33.0}]}, {"name": "fromages frais non affin\u00e9s", "children": [{"name": "fromage frais \u00e0 tartiner nature \u00e0 plus de 60% m.g.", "size": 20.0}, {"name": "boursin fromage frais sal\u00e9 aromatis\u00e9 70% m.g.", "size": 20.0}]}, {"name": "autres fromages ou fromage sans pr\u00e9cision", "children": [{"name": "autre fromage", "size": 12.5}]}]}]}